systest.py
systest-5.12.1.dist-info/LICENSE
systest-5.12.1.dist-info/METADATA
systest-5.12.1.dist-info/WHEEL
systest-5.12.1.dist-info/top_level.txt
systest-5.12.1.dist-info/RECORD
