Metadata-Version: 2.1
Name: systest
Version: 5.12.1
Summary: System test framework with serial and parallel execution.
Home-page: https://github.com/eerimoq/systest
Author: Erik Moqvist
Author-email: erik.moqvist@gmail.com
License: MIT
Keywords: test,system,sequencer,parallel
Platform: UNKNOWN
Classifier: License :: OSI Approved :: MIT License
Classifier: Programming Language :: Python :: 2
Classifier: Programming Language :: Python :: 3
Requires-Dist: humanfriendly
